peper/__main__.py
peper/bucket.py
test/__init__.py
test/test_main.py
peper-0.0.6.dist-info/LICENSE
peper-0.0.6.dist-info/METADATA
peper-0.0.6.dist-info/WHEEL
peper-0.0.6.dist-info/entry_points.txt
peper-0.0.6.dist-info/top_level.txt
peper-0.0.6.dist-info/RECORD
