Metadata-Version: 2.1
Name: peper
Version: 0.0.6
Summary: A bunch of recepies.
Home-page: https://github.com/ahhhhmed/peper
Author: Nenad
Author-email: Ahhhhmed@gmail.com
License: UNKNOWN
Platform: UNKNOWN
Classifier: Programming Language :: Python :: 3
Requires-Python: >=3.6
